mango/__init__.py
mango/agent/__init__.py
mango/agent/core.py
mango/agent/role.py
mango/container/__init__.py
mango/container/core.py
mango/container/external_coupling.py
mango/container/factory.py
mango/container/mp.py
mango/container/mqtt.py
mango/container/protocol.py
mango/container/tcp.py
mango/express/__init__.py
mango/express/api.py
mango/express/topology.py
mango/messages/__init__.py
mango/messages/acl_message_pb2.py
mango/messages/codecs.py
mango/messages/fast_json.py
mango/messages/mango_message_pb2.py
mango/messages/message.py
mango/messages/other_proto_msgs_pb2.py
mango/util/__init__.py
mango/util/clock.py
mango/util/distributed_clock.py
mango/util/multiprocessing.py
mango/util/scheduling.py
mango/util/termination_detection.py
mango_agents-2.1.5.dist-info/licenses/LICENSE
mango_agents-2.1.5.dist-info/METADATA
mango_agents-2.1.5.dist-info/WHEEL
mango_agents-2.1.5.dist-info/top_level.txt
mango_agents-2.1.5.dist-info/RECORD
