Metadata-Version: 2.4
Name: mango-agents
Version: 2.1.5
Summary: Modular Python Agent Framework
Author-email: mango Team <mango@offis.de>
License: MIT License
Project-URL: Homepage, https://mango-agents.readthedocs.io
Project-URL: Repository, https://github.com/OFFIS-DAI/mango
Project-URL: Issues, https://github.com/OFFIS-DAI/mango/issues
Classifier: License :: OSI Approved :: MIT License
Classifier: Programming Language :: Python
Classifier: Programming Language :: Python :: 3
Classifier: Programming Language :: Python :: 3.10
Classifier: Programming Language :: Python :: 3.11
Classifier: Programming Language :: Python :: 3.12
Classifier: Programming Language :: Python :: 3.13
Classifier: Programming Language :: Python :: Implementation :: CPython
Classifier: Programming Language :: Python :: Implementation :: PyPy
Requires-Python: >=3.10
License-File: LICENSE
Requires-Dist: paho-mqtt>=2.1.0
Requires-Dist: python-dateutil>=2.9.0
Requires-Dist: dill>=0.3.8
Requires-Dist: protobuf==5.27.2
Requires-Dist: networkx>=3.4.1
Provides-Extra: fastjson
Requires-Dist: msgspec>=0.18.6; extra == "fastjson"
Provides-Extra: test
Requires-Dist: pytest; extra == "test"
Requires-Dist: pytest-cov; extra == "test"
Requires-Dist: pytest-asyncio; extra == "test"
Requires-Dist: pre-commit; extra == "test"
Dynamic: license-file
